orchestrator/__init__.py
orchestrator/_env_loader.py
orchestrator/cli.py
orchestrator/config.py
orchestrator/context.py
orchestrator/observability.py
orchestrator/observability_jsonl_sink.py
orchestrator/py.typed
orchestrator/routing.py
orchestrator/_internal/__init__.py
orchestrator/_internal/errors.py
orchestrator/_internal/logger.py
orchestrator/_internal/public_legacy.py
orchestrator/_internal/runtime_validation.py
orchestrator/_internal/validation.py
orchestrator/_internal/agents/__init__.py
orchestrator/_internal/agents/agent.py
orchestrator/_internal/agents/discovery.py
orchestrator/_internal/agents/lifecycle.py
orchestrator/_internal/agents/messaging.py
orchestrator/_internal/agents/permissions.py
orchestrator/_internal/assessment/__init__.py
orchestrator/_internal/assessment/evaluation.py
orchestrator/_internal/auth/__init__.py
orchestrator/_internal/backends/__init__.py
orchestrator/_internal/backends/auth/__init__.py
orchestrator/_internal/backends/auth/base.py
orchestrator/_internal/backends/auth/none.py
orchestrator/_internal/backends/instruments/__init__.py
orchestrator/_internal/backends/instruments/base.py
orchestrator/_internal/backends/instruments/markdown.py
orchestrator/_internal/backends/llm/__init__.py
orchestrator/_internal/backends/llm/base.py
orchestrator/_internal/backends/llm/litellm.py
orchestrator/_internal/backends/observability/__init__.py
orchestrator/_internal/backends/observability/base.py
orchestrator/_internal/backends/observability/context_tracker.py
orchestrator/_internal/backends/observability/logging_backend.py
orchestrator/_internal/backends/observability/monitoring_backends.py
orchestrator/_internal/backends/profiles/__init__.py
orchestrator/_internal/backends/profiles/base.py
orchestrator/_internal/backends/profiles/file.py
orchestrator/_internal/backends/storage/__init__.py
orchestrator/_internal/backends/storage/base.py
orchestrator/_internal/backends/storage/file.py
orchestrator/_internal/backends/storage/memory.py
toolweaver-0.21.0.dist-info/licenses/LICENSE
toolweaver-0.21.0.dist-info/METADATA
toolweaver-0.21.0.dist-info/WHEEL
toolweaver-0.21.0.dist-info/entry_points.txt
toolweaver-0.21.0.dist-info/top_level.txt
toolweaver-0.21.0.dist-info/RECORD
