Metadata-Version: 2.4
Name: toolweaver
Version: 0.21.0
Summary: Production-ready AI tool orchestration with dynamic discovery, semantic search, and workflow composition. Requires Claude Agent SDK (proprietary) - users must supply API keys and comply with Anthropic's Commercial Terms.
Author-email: Usha Krishnan <ushapriya.krishnan@gmail.com>
License-Expression: Apache-2.0
Project-URL: Homepage, https://ushakrishnan.github.io/ToolWeaver
Project-URL: Documentation, https://ushakrishnan.github.io/ToolWeaver
Project-URL: Repository, https://github.com/ushakrishnan/ToolWeaver
Project-URL: Issues, https://github.com/ushakrishnan/ToolWeaver/issues
Project-URL: Changelog, https://github.com/ushakrishnan/ToolWeaver/releases
Keywords: ai,llm,orchestration,tools,mcp,workflows,semantic-search,prompt-engineering,cost-optimization
Classifier: Development Status :: 4 - Beta
Classifier: Intended Audience :: Developers
Classifier: Programming Language :: Python :: 3
Classifier: Programming Language :: Python :: 3.10
Classifier: Programming Language :: Python :: 3.11
Classifier: Programming Language :: Python :: 3.12
Classifier: Programming Language :: Python :: 3.13
Classifier: Topic :: Software Development :: Libraries :: Python Modules
Classifier: Topic :: Scientific/Engineering :: Artificial Intelligence
Requires-Python: >=3.10
License-File: LICENSE
Requires-Dist: pydantic>=2.7.0
Requires-Dist: aiohttp>=3.9.0
Requires-Dist: python-dotenv>=1.0.0
Requires-Dist: pyyaml>=6.0.0
Requires-Dist: requests>=2.31.0
Requires-Dist: numpy>=1.24.0
Requires-Dist: sentence-transformers>=2.2.0
Requires-Dist: rank-bm25>=0.2.2
Requires-Dist: mcp>=1.0.0
Requires-Dist: flask>=3.0.0
Requires-Dist: flask-cors>=4.0.0
Requires-Dist: anthropic>=0.25.0
Provides-Extra: azure
Requires-Dist: azure-ai-vision-imageanalysis>=1.0.0; extra == "azure"
Requires-Dist: azure-identity>=1.15.0; extra == "azure"
Provides-Extra: openai
Requires-Dist: openai>=1.0.0; extra == "openai"
Provides-Extra: wandb
Requires-Dist: wandb>=0.16.0; extra == "wandb"
Provides-Extra: prometheus
Requires-Dist: prometheus-client>=0.19.0; extra == "prometheus"
Provides-Extra: server
Requires-Dist: fastapi>=0.100.0; extra == "server"
Requires-Dist: uvicorn>=0.20.0; extra == "server"
Requires-Dist: httpx>=0.26.0; extra == "server"
Provides-Extra: visualization
Requires-Dist: pandas>=2.0.0; extra == "visualization"
Requires-Dist: plotly>=5.0.0; extra == "visualization"
Requires-Dist: pillow>=10.0.0; extra == "visualization"
Provides-Extra: monitoring
Requires-Dist: wandb>=0.16.0; extra == "monitoring"
Requires-Dist: prometheus-client>=0.19.0; extra == "monitoring"
Provides-Extra: qdrant
Requires-Dist: qdrant-client>=1.7.0; extra == "qdrant"
Provides-Extra: pinecone
Requires-Dist: pinecone-client>=3.0.0; extra == "pinecone"
Provides-Extra: vector-db
Requires-Dist: qdrant-client>=1.7.0; extra == "vector-db"
Provides-Extra: redis
Requires-Dist: redis>=5.0.0; extra == "redis"
Requires-Dist: hiredis>=2.3.0; extra == "redis"
Provides-Extra: gemini
Requires-Dist: google-generativeai>=0.3.0; extra == "gemini"
Provides-Extra: local-models
Requires-Dist: transformers>=4.36.0; extra == "local-models"
Requires-Dist: torch>=2.1.0; extra == "local-models"
Requires-Dist: accelerate>=0.25.0; extra == "local-models"
Provides-Extra: dev
Requires-Dist: pytest>=9.0.0; extra == "dev"
Requires-Dist: pytest-asyncio>=0.23.0; extra == "dev"
Requires-Dist: pytest-mock>=3.12.0; extra == "dev"
Requires-Dist: pytest-cov>=4.1.0; extra == "dev"
Requires-Dist: black>=24.0.0; extra == "dev"
Requires-Dist: ruff>=0.1.0; extra == "dev"
Requires-Dist: mypy>=1.8.0; extra == "dev"
Requires-Dist: types-PyYAML>=6.0.0; extra == "dev"
Requires-Dist: types-docker>=7.0.0; extra == "dev"
Requires-Dist: types-requests>=2.30.0; extra == "dev"
Requires-Dist: isort>=5.13.0; extra == "dev"
Provides-Extra: docs
Requires-Dist: mkdocs>=1.5.0; extra == "docs"
Requires-Dist: mkdocs-material>=9.5.0; extra == "docs"
Requires-Dist: mkdocstrings[python]>=0.24.0; extra == "docs"
Provides-Extra: all
Requires-Dist: wandb>=0.16.0; extra == "all"
Requires-Dist: prometheus-client>=0.19.0; extra == "all"
Requires-Dist: azure-ai-vision-imageanalysis>=1.0.0; extra == "all"
Requires-Dist: azure-identity>=1.15.0; extra == "all"
Requires-Dist: openai>=1.0.0; extra == "all"
Requires-Dist: anthropic>=0.18.0; extra == "all"
Requires-Dist: google-generativeai>=0.3.0; extra == "all"
Requires-Dist: qdrant-client>=1.7.0; extra == "all"
Requires-Dist: pinecone-client>=3.0.0; extra == "all"
Requires-Dist: redis>=5.0.0; extra == "all"
Requires-Dist: hiredis>=2.3.0; extra == "all"
Requires-Dist: transformers>=4.36.0; extra == "all"
Requires-Dist: torch>=2.1.0; extra == "all"
Requires-Dist: fastapi>=0.100.0; extra == "all"
Requires-Dist: uvicorn>=0.20.0; extra == "all"
Requires-Dist: httpx>=0.26.0; extra == "all"
Requires-Dist: pandas>=2.0.0; extra == "all"
Requires-Dist: plotly>=5.0.0; extra == "all"
Requires-Dist: pillow>=10.0.0; extra == "all"
Provides-Extra: integration
Requires-Dist: redis>=5.0.0; extra == "integration"
Requires-Dist: hiredis>=2.3.0; extra == "integration"
Requires-Dist: qdrant-client>=1.7.0; extra == "integration"
Requires-Dist: wandb>=0.16.0; extra == "integration"
Dynamic: license-file
